{"data":{"site":{"siteMetadata":{"title":"Gatsby Blog Tutorial Demo"}},"topics":{"edges":[{"node":{"frontmatter":{"categories":["javascript"],"tags":["javascript"]}}},{"node":{"frontmatter":{"categories":["javascript"],"tags":["javascript"]}}},{"node":{"frontmatter":{"categories":["immutable","javascript"],"tags":["javascript"]}}},{"node":{"frontmatter":{"categories":["immutable","javascript"],"tags":["immutable"]}}},{"node":{"frontmatter":{"categories":["momentJs","javascript"],"tags":["momentJs"]}}},{"node":{"frontmatter":{"categories":["nodeJS"],"tags":["nodeJS"]}}},{"node":{"frontmatter":{"categories":["reactjs"],"tags":["reactjs"]}}},{"node":{"frontmatter":{"categories":["reactjs","webpack"],"tags":["webpack"]}}},{"node":{"frontmatter":{"categories":["reactjs","redux"],"tags":["redux"]}}},{"node":{"frontmatter":{"categories":["reactjs"],"tags":["reactjs"]}}},{"node":{"frontmatter":{"categories":["javascript"],"tags":["javascript"]}}},{"node":{"frontmatter":{"categories":["sequelize"],"tags":["back end","node js","sequelize"]}}},{"node":{"frontmatter":{"categories":["cat1"],"tags":["greeting"]}}},{"node":{"frontmatter":{"categories":["cat2"],"tags":["egg","wiki"]}}},{"node":{"frontmatter":{"categories":["cat1"],"tags":["greeting","egg"]}}}]}}}